{
  "schema_version": "ops_program.v1",
  "name": "bent_bracket_5kg_6061T6_4mm",
  "description": "4mm 6061-T6 bent bracket with 4x M6 mount holes and stiffening ribs for 5 kg load.",
  "material": "Aluminum 6061-T6 sheet, t=4.0 mm \u00b10.2 mm, certified yield \u2265 276 MPa",
  "units": "mm",
  "stock": {
    "type": "block",
    "dimensions": {
      "x": 120,
      "y": 80,
      "z": 4
    }
  },
  "operations": [
    {
      "id": "op_001",
      "primitive": "hole",
      "description": "M6 clearance mounting holes on 60x40 pattern",
      "parameters": [
        {
          "name": "diameter",
          "value": 6.6,
          "unit": "mm"
        },
        {
          "name": "depth",
          "value": 4.0,
          "unit": "mm"
        }
      ],
      "position": {
        "x": 60,
        "y": 40,
        "z": 0
      },
      "annotations": {
        "quantity": "4",
        "pattern": "rectangular",
        "pattern_pitch_x": "60",
        "pattern_pitch_y": "40",
        "hole_tolerance": "+0.2/-0.0",
        "min_edge_distance": "\u226512",
        "process": "laser_cut",
        "tool_clearance_diameter": "\u226518",
        "tool_swing_clearance": "\u226530"
      }
    },
    {
      "id": "op_002",
      "primitive": "slot",
      "description": "Bend relief slots at main bend ends",
      "parameters": [
        {
          "name": "width",
          "value": 6.0,
          "unit": "mm"
        },
        {
          "name": "length",
          "value": 12.0,
          "unit": "mm"
        }
      ],
      "position": {
        "x": 60,
        "y": 20,
        "z": 0
      },
      "annotations": {
        "quantity": "2",
        "orientation": "along_y",
        "process": "laser_cut",
        "min_web_between_features": "\u226510",
        "hole_to_bend_distance": "\u22658",
        "inside_bend_radius": "\u22654.0",
        "bend_angle_tolerance": "\u00b11.0deg",
        "linear_tolerance": "\u00b10.5"
      }
    },
    {
      "id": "op_003",
      "primitive": "slot",
      "description": "Bend relief slots at lip bend ends",
      "parameters": [
        {
          "name": "width",
          "value": 6.0,
          "unit": "mm"
        },
        {
          "name": "length",
          "value": 12.0,
          "unit": "mm"
        }
      ],
      "position": {
        "x": 60,
        "y": 60,
        "z": 0
      },
      "annotations": {
        "quantity": "2",
        "orientation": "along_y",
        "process": "laser_cut",
        "min_web_between_features": "\u226510",
        "hole_to_bend_distance": "\u22658",
        "inside_bend_radius": "\u22654.0",
        "bend_angle_tolerance": "\u00b11.0deg",
        "linear_tolerance": "\u00b10.5"
      }
    },
    {
      "id": "op_004",
      "primitive": "rib",
      "description": "Stiffening ribs on vertical leg to limit deflection",
      "parameters": [
        {
          "name": "height",
          "value": 20.0,
          "unit": "mm"
        },
        {
          "name": "thickness",
          "value": 4.0,
          "unit": "mm"
        }
      ],
      "position": {
        "x": 60,
        "y": 40,
        "z": 0
      },
      "annotations": {
        "quantity": "2",
        "orientation": "vertical_leg",
        "rib_length": "70",
        "rib_spacing": "30",
        "purpose": "increase bending stiffness",
        "min_feature_size": "\u22651.0",
        "process": "formed_feature"
      }
    }
  ],
  "dfm_status": "DRAFT",
  "revision_notes": [
    "Formed sheet-metal bracket: 6061-T6, t=4.0\u00b10.2 mm; inside bend radius \u22654.0 mm; bend angle tolerance \u00b11.0\u00b0, linear \u00b10.5 mm.",
    "Assumed geometry: main L-bend creates 80 mm vertical leg (mounting plane) and 100 mm horizontal arm; optional 20 mm downturned lip at arm end for stiffness; load applied at arm end with moment arm \u2264100 mm.",
    "Rated load: 49.1 N downward at load interface; design targets: max von Mises \u226483 MPa, tip deflection \u22641.0 mm, angular rotation \u22640.5\u00b0 at rated load.",
    "Overload: 98.1 N downward for 60 s; requirement: no fracture and no fastener pull-out; mounting region maintains function.",
    "Mounting: 4x M6 clearance holes \u00d86.6 (+0.2/-0.0) on 60x40 mm pattern (\u00b10.5); minimum edge distance \u226512 mm; minimum web between features \u226510 mm; hole-to-bend distance \u22658 mm.",
    "Fasteners: M6 property class 8.8 (min). Tightening torque 10 N\u00b7m \u00b120%. Locking method required: medium-strength threadlocker (e.g., Loctite 243) or prevailing-torque locknut.",
    "Tool access: provide \u226518 mm diameter socket/wrench clearance around each fastener and \u226530 mm tool swing clearance.",
    "Finish: clear anodize 10 \u00b5m \u00b13 \u00b5m per ISO 2360; corrosion screening target ASTM B117 96 h no base metal corrosion (cosmetic staining acceptable).",
    "Deburr/break edges: all external edges and holes edge break 0.5 mm \u00b10.3 mm; burr height \u22640.1 mm.",
    "Mass target: \u22640.5 kg (4 mm aluminum sheet bracket within 120x80 blank meets target)."
  ],
  "_run_id": 1770308290,
  "generated_cadquery_code": "import cadquery as cq\n\n# Parameters (mm)\nlength = 120.0\nwidth = 80.0\nthickness = 4.0\n\nhole_d = 6.6\nhole_depth = 4.0\n\nslot_len = 12.0\nslot_w = 6.0\n\nrib_len = 70.0\nrib_thk = 4.0\nrib_h = 20.0\n\n# Coordinate conversion:\n# Ops positions are given in a 0..length / 0..width system.\n# CadQuery box is centered at origin, so shift by (-length/2, -width/2).\ndef to_centered_xy(x, y):\n    return (x - length / 2.0, y - width / 2.0)\n\n# Feature locations (mm) in absolute (0..length / 0..width) coordinates\nhole_positions_abs = [(30.0, 20.0), (90.0, 20.0), (30.0, 60.0), (90.0, 60.0)]\nslot_main_abs = [(6.0, 20.0), (114.0, 20.0)]\nslot_lip_abs = [(6.0, 60.0), (114.0, 60.0)]\nrib1_center_abs = (60.0, 25.0)\nrib2_center_abs = (60.0, 55.0)\n\n# Convert to centered coordinates for standard face-centered workplanes\nhole_positions = [to_centered_xy(x, y) for x, y in hole_positions_abs]\nslot_main_positions = [to_centered_xy(x, y) for x, y in slot_main_abs]\nslot_lip_positions = [to_centered_xy(x, y) for x, y in slot_lip_abs]\nrib1_center = to_centered_xy(*rib1_center_abs)\nrib2_center = to_centered_xy(*rib2_center_abs)\n\n# 1) Stock geometry\nresult = cq.Workplane(\"XY\").box(length, width, thickness)\n\n# 2-3) Top face: mounting holes\nresult = (\n    result.faces(\">Z\")\n    .workplane()\n    .pushPoints(hole_positions)\n    .hole(hole_d, depth=hole_depth)\n)\n\n# 4-5) Main bend relief slots (along Y => angle=90 deg), cut through\nresult = (\n    result.faces(\">Z\")\n    .workplane()\n    .pushPoints(slot_main_positions)\n    .slot2D(slot_len, slot_w, angle=90.0)\n    .cutThruAll()\n)\n\n# 6-7) Lip bend relief slots (along Y), cut through\nresult = (\n    result.faces(\">Z\")\n    .workplane()\n    .pushPoints(slot_lip_positions)\n    .slot2D(slot_len, slot_w, angle=90.0)\n    .cutThruAll()\n)\n\n# 8-12) Ribs on top face (two rectangles), extrude upward\n# Root cause: rib coordinates were in absolute space but applied on a centered workplane\n# (or mixed with origin shifting), placing rib sketches off the plate -> disconnected solids.\n# Fix: use centered coordinates on the default face-centered workplane.\nresult = (\n    result.faces(\">Z\")\n    .workplane()\n    .center(rib1_center[0], rib1_center[1])\n    .rect(rib_len, rib_thk, centered=True)\n    .extrude(rib_h)\n)\n\nresult = (\n    result.faces(\">Z\")\n    .workplane()\n    .center(rib2_center[0], rib2_center[1])\n    .rect(rib_len, rib_thk, centered=True)\n    .extrude(rib_h)\n)",
  "pipeline_trace": {
    "success": true,
    "confidence": 0.7649999999999999,
    "execution": {
      "iterations": 3,
      "final_success": true,
      "error": null,
      "issues": [
        {
          "iteration": 1,
          "issue": "disconnected_geometry",
          "issue_details": {
            "solid_count": 2,
            "bounds_hint": "x \u2208 [-60.0, 60.0], y \u2208 [-40.0, 40.0]"
          },
          "fix_applied": "Disconnected geometry fix: 2 solids"
        },
        {
          "iteration": 2,
          "issue": "disconnected_geometry",
          "issue_details": {
            "solid_count": 2,
            "bounds_hint": "x \u2208 [-60.0, 60.0], y \u2208 [-40.0, 40.0]"
          },
          "fix_applied": "Disconnected geometry fix: 2 solids"
        },
        {
          "iteration": 3,
          "issue": "disconnected_geometry",
          "issue_details": {
            "solid_count": 2,
            "bounds_hint": "x \u2208 [-60.0, 60.0], y \u2208 [-40.0, 40.0]"
          },
          "fix_applied": "Disconnected geometry fix: 2 solids"
        }
      ]
    },
    "decomposition": {
      "overall_confidence": 0.56,
      "num_operations": 12,
      "operations": [
        {
          "primitive": "box",
          "description": "Create stock sheet block",
          "confidence": 1.0,
          "parameters": [
            {
              "name": "length",
              "value": 120,
              "unit": "mm"
            },
            {
              "name": "width",
              "value": 80,
              "unit": "mm"
            },
            {
              "name": "height",
              "value": 4,
              "unit": "mm"
            }
          ]
        },
        {
          "primitive": "select_face",
          "description": "Select top face for cut features",
          "confidence": 1.0,
          "parameters": [
            {
              "name": "direction",
              "value": ">Z",
              "unit": null
            }
          ]
        },
        {
          "primitive": "hole",
          "description": "Create 4 mounting holes on 60x40 pattern",
          "confidence": 0.72,
          "parameters": [
            {
              "name": "diameter",
              "value": 6.6,
              "unit": "mm"
            },
            {
              "name": "depth",
              "value": 4.0,
              "unit": "mm"
            },
            {
              "name": "positions",
              "value": [
                [
                  30,
                  20
                ],
                [
                  90,
                  20
                ],
                [
                  30,
                  60
                ],
                [
                  90,
                  60
                ]
              ],
              "unit": "mm"
            }
          ]
        },
        {
          "primitive": "sketch_slot",
          "description": "Sketch 2 bend relief slots at main bend ends",
          "confidence": 0.55,
          "parameters": [
            {
              "name": "length",
              "value": 12.0,
              "unit": "mm"
            },
            {
              "name": "width",
              "value": 6.0,
              "unit": "mm"
            },
            {
              "name": "positions",
              "value": [
                [
                  6,
                  20
                ],
                [
                  114,
                  20
                ]
              ],
              "unit": "mm"
            },
            {
              "name": "orientation",
              "value": "along_y",
              "unit": null
            }
          ]
        },
        {
          "primitive": "extrude_cut",
          "description": "Cut main bend relief slots through thickness",
          "confidence": 0.7,
          "parameters": [
            {
              "name": "height",
              "value": 4.0,
              "unit": "mm"
            },
            {
              "name": "direction",
              "value": "-Z",
              "unit": null
            }
          ]
        },
        {
          "primitive": "sketch_slot",
          "description": "Sketch 2 bend relief slots at lip bend ends",
          "confidence": 0.55,
          "parameters": [
            {
              "name": "length",
              "value": 12.0,
              "unit": "mm"
            },
            {
              "name": "width",
              "value": 6.0,
              "unit": "mm"
            },
            {
              "name": "positions",
              "value": [
                [
                  6,
                  60
                ],
                [
                  114,
                  60
                ]
              ],
              "unit": "mm"
            },
            {
              "name": "orientation",
              "value": "along_y",
              "unit": null
            }
          ]
        },
        {
          "primitive": "extrude_cut",
          "description": "Cut lip bend relief slots through thickness",
          "confidence": 0.7,
          "parameters": [
            {
              "name": "height",
              "value": 4.0,
              "unit": "mm"
            },
            {
              "name": "direction",
              "value": "-Z",
              "unit": null
            }
          ]
        },
        {
          "primitive": "select_face",
          "description": "Select top face for ribs",
          "confidence": 0.9,
          "parameters": [
            {
              "name": "direction",
              "value": ">Z",
              "unit": null
            }
          ]
        },
        {
          "primitive": "sketch_rectangle",
          "description": "Sketch rib 1 footprint",
          "confidence": 0.35,
          "parameters": [
            {
              "name": "width",
              "value": 70,
              "unit": "mm"
            },
            {
              "name": "height",
              "value": 4.0,
              "unit": "mm"
            },
            {
              "name": "center",
              "value": [
                60,
                25
              ],
              "unit": "mm"
            }
          ]
        },
        {
          "primitive": "extrude",
          "description": "Extrude rib 1 upward",
          "confidence": 0.55,
          "parameters": [
            {
              "name": "height",
              "value": 20.0,
              "unit": "mm"
            },
            {
              "name": "direction",
              "value": "+Z",
              "unit": null
            }
          ]
        },
        {
          "primitive": "sketch_rectangle",
          "description": "Sketch rib 2 footprint",
          "confidence": 0.35,
          "parameters": [
            {
              "name": "width",
              "value": 70,
              "unit": "mm"
            },
            {
              "name": "height",
              "value": 4.0,
              "unit": "mm"
            },
            {
              "name": "center",
              "value": [
                60,
                55
              ],
              "unit": "mm"
            }
          ]
        },
        {
          "primitive": "extrude",
          "description": "Extrude rib 2 upward",
          "confidence": 0.55,
          "parameters": [
            {
              "name": "height",
              "value": 20.0,
              "unit": "mm"
            },
            {
              "name": "direction",
              "value": "+Z",
              "unit": null
            }
          ]
        }
      ],
      "ambiguities": [
        "Hole pattern origin not fully specified; interpreted as centered about stock center with 60x40 pitch.",
        "Bend relief slot X locations not specified; placed near left/right edges with 6 mm margin.",
        "Ribs described as on vertical leg of a bent bracket, but no bend operation exists; ribs modeled as extrusions on flat stock.",
        "Rib footprint orientation and exact placement not specified; assumed two ribs spaced 30 mm in Y with 70x4 footprint."
      ],
      "assumptions": [
        "Units are millimeters.",
        "Stock box is centered at origin in CadQuery.",
        "All holes/slots are through the 4 mm thickness.",
        "Slots are oriented along Y (slot major axis along Y).",
        "Ribs are simple rectangular extrusions (no formed bead geometry).",
        "Fillets/chamfers/deburr are intentionally omitted per system rule."
      ]
    },
    "retrieval": {
      "apis_used": [
        "extrude",
        "workplane",
        "rect",
        "loft",
        "cutBlind",
        "slot2D",
        "cboreHole",
        "shell",
        "box",
        "hole",
        "faces",
        "cutThruAll",
        "fillet",
        "edges",
        "moveTo",
        "transformed",
        "center",
        "chamfer",
        "pushPoints"
      ],
      "per_operation": [
        {
          "op_index": 0,
          "apis": [
            "box",
            "loft",
            "slot2D"
          ],
          "top_score": 0.6974956285582306
        },
        {
          "op_index": 1,
          "apis": [
            "faces",
            "edges",
            "cutThruAll"
          ],
          "top_score": 0.8064842931242178
        },
        {
          "op_index": 2,
          "apis": [
            "pushPoints",
            "hole",
            "cboreHole"
          ],
          "top_score": 0.7496200351101506
        },
        {
          "op_index": 3,
          "apis": [
            "slot2D",
            "chamfer",
            "loft"
          ],
          "top_score": 0.7939958883464557
        },
        {
          "op_index": 4,
          "apis": [
            "cutThruAll",
            "cutBlind",
            "slot2D"
          ],
          "top_score": 0.7761039556693023
        },
        {
          "op_index": 5,
          "apis": [
            "slot2D",
            "chamfer",
            "loft"
          ],
          "top_score": 0.7923297042349193
        },
        {
          "op_index": 6,
          "apis": [
            "cutThruAll",
            "cutBlind",
            "shell"
          ],
          "top_score": 0.7836105573105254
        },
        {
          "op_index": 7,
          "apis": [
            "faces",
            "edges",
            "fillet"
          ],
          "top_score": 0.8016116772809451
        },
        {
          "op_index": 8,
          "apis": [
            "rect",
            "slot2D",
            "loft"
          ],
          "top_score": 0.7285476643933136
        },
        {
          "op_index": 9,
          "apis": [
            "extrude",
            "cutThruAll",
            "loft"
          ],
          "top_score": 0.7916850081593885
        },
        {
          "op_index": 10,
          "apis": [
            "rect",
            "slot2D",
            "loft"
          ],
          "top_score": 0.7271626841729475
        },
        {
          "op_index": 11,
          "apis": [
            "extrude",
            "loft",
            "cutThruAll"
          ],
          "top_score": 0.7948682241442682
        }
      ]
    },
    "synthesis": {
      "confidence": 0.7649999999999999,
      "iterations": 1
    }
  }
}